pose_db_io/__init__.py
pose_db_io/config.py
pose_db_io/core.py
pose_db_io/handle/__init__.py
pose_db_io/handle/handle.py
pose_db_io/handle/models/pose_2d.py
pose_db_io/handle/models/pose_3d.py
pose_db_io/handle/models/pose_track_3d.py
pose_db_io/handle/models/pose_track_3d_pose_3d_link.py
pose_db_io/log.py
wf_pose_db_io-0.1.4.dist-info/LICENSE
wf_pose_db_io-0.1.4.dist-info/METADATA
wf_pose_db_io-0.1.4.dist-info/WHEEL
wf_pose_db_io-0.1.4.dist-info/RECORD
