Metadata-Version: 2.1
Name: wf-pose-db-io
Version: 0.1.4
Summary: Tools for working with data in Wildflower's pose database
Home-page: https://github.com/WildflowerSchools/wf-pose-db-io>
License: MIT
Author: btalberg
Author-email: ben.talberg@gmail.com
Maintainer: btalberg
Maintainer-email: ben.talberg@gmail.com
Requires-Python: >=3.9,<4.0
Classifier: Intended Audience :: Developers
Classifier: License :: OSI Approved :: MIT License
Classifier: Operating System :: OS Independent
Classifier: Programming Language :: Python
Classifier: Programming Language :: Python :: 3
Classifier: Programming Language :: Python :: 3.9
Classifier: Programming Language :: Python :: 3.10
Classifier: Programming Language :: Python :: 3.11
Classifier: Programming Language :: Python :: 3.12
Requires-Dist: numpy (>=1.26.2,<2.0.0)
Requires-Dist: pandas (>=2.1.3,<3.0.0)
Requires-Dist: pydantic (>=2.4.2,<3.0.0)
Requires-Dist: pydantic-settings (>=2.0.3,<3.0.0)
Requires-Dist: pymongo (>=4.6.0,<5.0.0)
Requires-Dist: toml (>=0.10.2,<0.11.0)
Project-URL: Repository, https://github.com/WildflowerSchools/wf-pose-db-io>
